[
  {
    "//comment": "DO NOT MODIFY",
    "cluster_name": "myFirstCluster",
    "ARN": "arn:aws:rds:us-east-2:123456789012:db:my-mysql-instance-A",
    "Endpoint": "foo-3f71e9.clrb45fomzui.us-east-2.rds.amazonaws.com:3306",
    "org": "Colton Labs"
  },
  {
    "//comment": "DO NOT MODIFY",
    "cluster_name": "clusterB",
    "ARN": "arn:aws:rds:us-east-2:123456789012:db:my-mysql-instance-B",
    "Endpoint": "bar-7f71e9.clrb45fomzui.us-east-2.rds.amazonaws.com:3306",
    "org": "Quickstart-org-2"
  },
  {
    "cluster_name": "clusterC",
    "ARN": "arn:aws:rds:us-east-2:123456789012:db:my-mysql-instance-C",
    "Endpoint": "baz-8f81a2.clrb45fomzui.us-east-2.rds.amazonaws.com:3306",
    "org": "Colton Labs"
  }
]
